pyforce/__init__.py
pyforce/common.py
pyforce/marshall.py
pyforce/pyclient.py
pyforce/xmlclient.py
pyforce/xmltramp.py
pyforce-1.9.1.dist-info/LICENSE.txt
pyforce-1.9.1.dist-info/METADATA
pyforce-1.9.1.dist-info/WHEEL
pyforce-1.9.1.dist-info/top_level.txt
pyforce-1.9.1.dist-info/RECORD
