Metadata-Version: 2.1
Name: pyforce
Version: 1.9.1
Summary: A Python client wrapping the Salesforce.com SOAP API
Home-page: https://github.com/alanjcastonguay/pyforce
Author: Simon Fell et al.  reluctantly Forked by idbentley
Author-email: ian.bentley@gmail.com, alanjcastonguay@gmail.com
License: GNU GENERAL PUBLIC LICENSE Version 2
Keywords: python salesforce salesforce.com
Platform: UNKNOWN
Classifier: Development Status :: 5 - Production/Stable
Classifier: Intended Audience :: Developers
Classifier: Programming Language :: Python :: 2
Classifier: Programming Language :: Python :: 2.7
Classifier: Programming Language :: Python :: 3
Classifier: Programming Language :: Python :: 3.5
Classifier: Programming Language :: Python :: 3.6
Classifier: Programming Language :: Python :: 3.7
Requires-Dist: defusedxml (>=0.5.0)
Requires-Dist: requests (>=2.0.0)
Requires-Dist: six (>=1.10.0)
